lexc2dix/__init__.py
lexc2dix/dix_generator.py
lexc2dix/lexc_parser.py
lexc2dix/release.py
lexc2dix/py2xml/__init__.py
lexc2dix/py2xml/serializer.py
lexc2dix-1.0.data/scripts/lexc2dix_api.py
lexc2dix-1.0.dist-info/DESCRIPTION.rst
lexc2dix-1.0.dist-info/METADATA
lexc2dix-1.0.dist-info/RECORD
lexc2dix-1.0.dist-info/WHEEL
lexc2dix-1.0.dist-info/entry_points.txt
lexc2dix-1.0.dist-info/metadata.json
lexc2dix-1.0.dist-info/top_level.txt
