Metadata-Version: 2.0
Name: lexc2dix
Version: 1.0
Summary: The python module for converting lexc to dix files format
Home-page: https://github.com/Techievena/lexc2dix
Author: Abinash Senapati(@Techievena)
Author-email: abinashsena@gmail.com
License: GNU GENERAL PUBLIC LICENSE
Download-URL: https://github.com/Techievena/lexc2dix/archive/master.zip
Keywords: lexc,twolc,monodix,Apertium,HFST
Platform: UNKNOWN
Classifier: Development Status :: 3 - Alpha
Classifier: Intended Audience :: Developers
Classifier: Topic :: Software Development :: Build Tools
Classifier: License :: OSI Approved :: GNU General Public License v3 (GPLv3)
Classifier: Programming Language :: Python :: 3
Classifier: Programming Language :: Python :: 3.2
Classifier: Programming Language :: Python :: 3.3
Classifier: Programming Language :: Python :: 3.4
Requires-Python: >=3
Requires-Dist: regex
